LICENSE
README.md
setup.cfg
setup.py
python4poets/__init__.py
python4poets/python4poets.py
python4poets.egg-info/PKG-INFO
python4poets.egg-info/SOURCES.txt
python4poets.egg-info/dependency_links.txt
python4poets.egg-info/requires.txt
python4poets.egg-info/top_level.txt