Metadata-Version: 2.1
Name: python4poets
Version: 0.2
Summary: Code and resources for poets writing python
Home-page: https://github.com/Princeton-CDH/python4poets
Author: The Center for Digital Humanities at Princeton
Author-email: cdhdevteam@princeton.edu
License: Apache License, Version 2.0
Project-URL: Project Home, https://cdh.princeton.edu/
Project-URL: Bug Tracker, https://github.com/Princeton-CDH/python4poets/issues
Platform: UNKNOWN
Classifier: Development Status :: 2 - Pre-Alpha
Classifier: Programming Language :: Python :: 3
Classifier: Intended Audience :: Developers
Classifier: License :: OSI Approved :: Apache Software License
Classifier: Operating System :: OS Independent
Classifier: Topic :: Software Development :: Libraries :: Python Modules
Requires-Python: >=3.8
Provides-Extra: all
Provides-Extra: dev
Provides-Extra: test
